simple_af/__init__.py
simple_af/__main__.py
simple_af/_keyboard.py
simple_af/_opc.py
simple_af/fountain_models.py
simple_af/framework.py
simple_af/launcher.py
simple_af/layout.py
simple_af/model.py
simple_af/osc_utils.py
simple_af/pixels.py
simple_af/state.py
simple_af/utils.py
simple_af/plugins/midi/__init__.py
simple_af/plugins/midi/midi_utils.py
simple_af/plugins/stock_effects/__init__.py
simple_af/plugins/stock_effects/bitmap.py
simple_af/plugins/stock_effects/example.py
simple_af/plugins/stock_effects/midi_effects.py
simple_af/plugins/stock_effects/scenes.py
simple_af/plugins/stock_effects/wip.py
simple_af-0.1.0.dist-info/METADATA
simple_af-0.1.0.dist-info/RECORD
simple_af-0.1.0.dist-info/WHEEL
simple_af-0.1.0.dist-info/entry_points.txt
simple_af-0.1.0.dist-info/top_level.txt
